risticks/__init__.py
risticks/main.py
risticks-1.0.1.dist-info/LICENSE
risticks-1.0.1.dist-info/METADATA
risticks-1.0.1.dist-info/WHEEL
risticks-1.0.1.dist-info/top_level.txt
risticks-1.0.1.dist-info/RECORD
