Metadata-Version: 2.1
Name: risticks
Version: 1.0.1
Summary: Библиотека для удобной работы с API Risticks
Home-page: https://github.com/pip64/risticks-api
Author: pip64, ierhon
Author-email: mrpip64@mail.ru
License: UNKNOWN
Platform: UNKNOWN
Classifier: Programming Language :: Python :: 3.8
Classifier: License :: OSI Approved :: MIT License
Classifier: Operating System :: OS Independent
Requires-Python: >=3.8
License-File: LICENSE
Requires-Dist: requests (>=2.21.0)
